<?xml version="1.0" ?>
<defaultcomment xmlns:xsi="http://www.w3.org/2001/XMLSchema-instance">
    <username>超级玛丽和奥特曼</username>
    <usercontrib>贡献值50-99</usercontrib>
    <rankrst>20</rankrst>
    <average>人均  ￥70 </average>
    <rst1>(好)</rst1>
    <rst2>(好)</rst2>
    <rst3>(好)</rst3>
    <content>鱼头泡饼很棒，环境还可以味道，宫保鸡丁和孜然羊肉做的不错 去中关村吃过一次
</content>
    <recommend-dish-list/>
    <tags/>
    <favorate-dish-list>
        <dish>鱼头泡饼</dish>
    </favorate-dish-list>
    <special-list>
        <special>无线上网</special>
        <special>是老字号</special>
    </special-list>
    <car-stop-info/>
    <atmosphere-list/>
    <time>03-05</time>
    <zan_count>1</zan_count>
    <reply_count>
</reply_count>
</defaultcomment>
