<?xml version="1.0" ?>
<defaultcomment xmlns:xsi="http://www.w3.org/2001/XMLSchema-instance">
    <username>晓霞6552</username>
    <usercontrib></usercontrib>
    <rankrst>50</rankrst>
    <average>人均  ￥70 </average>
    <rst1>(非常好)</rst1>
    <rst2>(非常好)</rst2>
    <rst3>(非常好)</rst3>
    <content>还不错~就是服务员太少，在包间里，几乎每10分钟就得出来找一次服务员~最过分的是当天说什么点菜系统出了问题，我们的很多菜说系统没有显示，居然过了一个小时才再再三催促后刚开始做
</content>
    <recommend-dish-list/>
    <tags/>
    <favorate-dish-list>
        <dish>鱼头泡饼</dish>
    </favorate-dish-list>
    <special-list>
        <special>可以刷卡</special>
    </special-list>
    <car-stop-info/>
    <atmosphere-list/>
    <time>13-12-09</time>
    <zan_count>1</zan_count>
    <reply_count>
</reply_count>
</defaultcomment>
