<?xml version="1.0" ?>
<defaultcomment xmlns:xsi="http://www.w3.org/2001/XMLSchema-instance">
    <username>LeonscorMax</username>
    <usercontrib>贡献值400-999</usercontrib>
    <rankrst>50</rankrst>
    <average>人均  ￥80 </average>
    <rst1>(非常好)</rst1>
    <rst2>(非常好)</rst2>
    <rst3>(非常好)</rst3>
    <content>因为旅游做了功课，这家店推荐的人很多，所以也来凑凑热闹。没想到味道真的很不错。非常喜欢 .
</content>
    <recommend-dish-list/>
    <tags/>
    <favorate-dish-list/>
    <special-list/>
    <car-stop-info/>
    <atmosphere-list/>
    <time>02-18</time>
    <zan_count>2</zan_count>
    <reply_count>
</reply_count>
</defaultcomment>
