<?xml version="1.0" ?>
<defaultcomment xmlns:xsi="http://www.w3.org/2001/XMLSchema-instance">
    <username>柒星儿</username>
    <usercontrib>贡献值100-199</usercontrib>
    <rankrst>20</rankrst>
    <average>人均  ￥68 </average>
    <rst1>(很好)</rst1>
    <rst2>(很好)</rst2>
    <rst3>(很好)</rst3>
    <content>鱼头泡饼！鱼头泡饼！鱼头泡饼！老店在朝内，没想到中关村这边也看了一家，很可以吃的家常菜。经典的鱼头泡饼，他家烤鸭也不错
</content>
    <recommend-dish-list/>
    <tags/>
    <favorate-dish-list>
        <dish>鱼头泡饼</dish>
        <dish>烤鸭</dish>
    </favorate-dish-list>
    <special-list/>
    <car-stop-info/>
    <atmosphere-list/>
    <time>03-13</time>
    <zan_count>1</zan_count>
    <reply_count>(1)
</reply_count>
</defaultcomment>
